ipc_thread/IPC.py
ipc_thread/IPCThread.py
ipc_thread/SingletonMeta.py
ipc_thread/__init__.py
ipc_thread/dev_IPC.py
bluenav_ipc_thread-0.1.5.dist-info/LICENSE
bluenav_ipc_thread-0.1.5.dist-info/METADATA
bluenav_ipc_thread-0.1.5.dist-info/WHEEL
bluenav_ipc_thread-0.1.5.dist-info/top_level.txt
bluenav_ipc_thread-0.1.5.dist-info/RECORD
