Metadata-Version: 2.1
Name: bluenav-ipc-thread
Version: 0.1.5
Summary: AWS wrapper around IPC
Author: bluedev
Author-email: theo.lanique@bluenav.fr
Classifier: Programming Language :: Python :: 3
Classifier: License :: OSI Approved :: MIT License
Classifier: Operating System :: OS Independent
Requires-Python: >=3.6
License-File: LICENSE
Requires-Dist: redis
Requires-Dist: awsiotsdk
